pendulum-stubs/__init__.pyi
pendulum-stubs/__version__.pyi
pendulum-stubs/_extensions/__init__.pyi
pendulum-stubs/_extensions/helpers.pyi
pendulum-stubs/constants.pyi
pendulum-stubs/date.pyi
pendulum-stubs/datetime.pyi
pendulum-stubs/duration.pyi
pendulum-stubs/exceptions.pyi
pendulum-stubs/formatting/__init__.pyi
pendulum-stubs/formatting/difference_formatter.pyi
pendulum-stubs/formatting/formatter.pyi
pendulum-stubs/helpers.pyi
pendulum-stubs/locales/__init__.pyi
pendulum-stubs/locales/da/__init__.pyi
pendulum-stubs/locales/da/custom.pyi
pendulum-stubs/locales/da/locale.pyi
pendulum-stubs/locales/de/__init__.pyi
pendulum-stubs/locales/de/custom.pyi
pendulum-stubs/locales/de/locale.pyi
pendulum-stubs/locales/en/__init__.pyi
pendulum-stubs/locales/en/custom.pyi
pendulum-stubs/locales/en/locale.pyi
pendulum-stubs/locales/es/__init__.pyi
pendulum-stubs/locales/es/custom.pyi
pendulum-stubs/locales/es/locale.pyi
pendulum-stubs/locales/fa/__init__.pyi
pendulum-stubs/locales/fa/custom.pyi
pendulum-stubs/locales/fa/locale.pyi
pendulum-stubs/locales/fo/__init__.pyi
pendulum-stubs/locales/fo/custom.pyi
pendulum-stubs/locales/fo/locale.pyi
pendulum-stubs/locales/fr/__init__.pyi
pendulum-stubs/locales/fr/custom.pyi
pendulum-stubs/locales/fr/locale.pyi
pendulum-stubs/locales/ko/__init__.pyi
pendulum-stubs/locales/ko/custom.pyi
pendulum-stubs/locales/ko/locale.pyi
pendulum-stubs/locales/locale.pyi
pendulum-stubs/locales/lt/__init__.pyi
pendulum-stubs/locales/lt/custom.pyi
pendulum-stubs/locales/lt/locale.pyi
pendulum-stubs/locales/pt_br/__init__.pyi
pendulum-stubs/locales/pt_br/custom.pyi
pendulum-stubs/locales/pt_br/locale.pyi
pendulum-stubs/locales/zh/__init__.pyi
pendulum-stubs/locales/zh/custom.pyi
pendulum-stubs/locales/zh/locale.pyi
pendulum-stubs/mixins/__init__.pyi
pendulum-stubs/mixins/default.pyi
pendulum-stubs/parser.pyi
pendulum-stubs/parsing/__init__.pyi
pendulum-stubs/parsing/exceptions/__init__.pyi
pendulum-stubs/parsing/iso8601.pyi
pendulum-stubs/period.pyi
pendulum_types-0.0.1.dist-info/METADATA
pendulum_types-0.0.1.dist-info/WHEEL
pendulum_types-0.0.1.dist-info/RECORD
